SaGaF_Email/SaGaF_Email.py
SaGaF_Email/__init__.py
SaGaF_Email-0.1.dist-info/METADATA
SaGaF_Email-0.1.dist-info/WHEEL
SaGaF_Email-0.1.dist-info/top_level.txt
SaGaF_Email-0.1.dist-info/RECORD
