Metadata-Version: 2.1
Name: SaGaF-Email
Version: 0.1
Summary: Checking emails for any domain , for example : gmail,yahoo,aol,hotmail,outlook,mail_ru
Author: @CCIIUU
Author-email: dxa00776@gmail.com
Classifier: Programming Language :: Python :: 3
Classifier: Operating System :: OS Independent
Classifier: License :: OSI Approved :: MIT License
